pywaves_curve25519.cpython-39-x86_64-linux-gnu.so
pywaves_curve25519-1.0.3.dist-info/METADATA
pywaves_curve25519-1.0.3.dist-info/WHEEL
pywaves_curve25519-1.0.3.dist-info/top_level.txt
pywaves_curve25519-1.0.3.dist-info/RECORD
pywaves_curve25519-1.0.3.dist-info/licenses/LICENSE
