Metadata-Version: 2.4
Name: PyWaves-Curve25519
Version: 1.0.3
Summary: Curve25519 (Ed25519 sign/verify with X25519 keys) for Waves blockchain
Home-page: https://github.com/PyWaves-CE/PyWaves-Curve25519
Author: Tarek Galal
Author-email: tare2.galal@gmail.com
License: GPL-3.0
Project-URL: Bug Reports, https://github.com/PyWaves-CE/PyWaves-Curve25519/issues
Project-URL: Source, https://github.com/PyWaves-CE/PyWaves-Curve25519
Keywords: cryptography curve25519 ed25519 x25519 pywaves waves blockchain
Platform: any
Classifier: Development Status :: 5 - Production/Stable
Classifier: Intended Audience :: Developers
Classifier: Programming Language :: Python :: 3
Classifier: Programming Language :: Python :: 3.8
Classifier: Programming Language :: Python :: 3.9
Classifier: Programming Language :: Python :: 3.10
Classifier: Programming Language :: Python :: 3.11
Classifier: Programming Language :: Python :: 3.12
Classifier: Programming Language :: Python :: 3.13
Classifier: Topic :: Security :: Cryptography
Requires-Python: >=3.8
License-File: LICENSE
Dynamic: author
Dynamic: author-email
Dynamic: classifier
Dynamic: description
Dynamic: description-content-type
Dynamic: home-page
Dynamic: keywords
Dynamic: license
Dynamic: license-file
Dynamic: platform
Dynamic: project-url
Dynamic: requires-python
Dynamic: summary
